<?xml version="1.0" encoding="UTF-8"?>
<tips>
<meeting date="26-02-2023" venue="ST" title="心水提供"/>
<race num="1">
<Tip Position="1" RunnerNumber="4" NameE="NICE BIRDIE" NameC="樂捉鳥" JockeyNameE="Z Purton" JockeyNameC="潘頓"/>
<Tip Position="2" RunnerNumber="11" NameE="GREEN LASER" NameC="綠登" JockeyNameE="C Y Ho" JockeyNameC="何澤堯"/>
<Tip Position="3" RunnerNumber="10" NameE="M M NEBULA" NameC="美滿星雲" JockeyNameE="M F Poon" JockeyNameC="潘明輝"/>
<Tip Position="4" RunnerNumber="6" NameE="BILLIONAIRE SECRET" NameC="發財秘笈" JockeyNameE="J Kah" JockeyNameC="賈傑美"/>
</race>
<race num="2">
<Tip Position="1" RunnerNumber="6" NameE="NORDIC STAR" NameC="雪山神駒" JockeyNameE="Z Purton" JockeyNameC="潘頓"/>
<Tip Position="2" RunnerNumber="4" NameE="ROYAL BOMB" NameC="王炸" JockeyNameE="J Kah" JockeyNameC="賈傑美"/>
<Tip Position="3" RunnerNumber="2" NameE="SO WE JOY" NameC="無心睡眠" JockeyNameE="C Y Ho" JockeyNameC="何澤堯"/>
<Tip Position="4" RunnerNumber="8" NameE="SKYEY SUPREME" NameC="雙天至尊" JockeyNameE="H N Wong" JockeyNameC="黃皓楠"/>
</race>
<race num="3">
<Tip Position="1" RunnerNumber="1" NameE="FANTASTIC TREASURE" NameC="佳運財" JockeyNameE="L Hewitson" JockeyNameC="希威森"/>
<Tip Position="2" RunnerNumber="5" NameE="ALL FOR ST PAUL'S" NameC="保羅承傳" JockeyNameE="M Chadwick" JockeyNameC="蔡明紹"/>
<Tip Position="3" RunnerNumber="6" NameE="CALIFORNIA TEN" NameC="加州十大" JockeyNameE="L Ferraris" JockeyNameC="霍宏聲"/>
<Tip Position="4" RunnerNumber="9" NameE="BEAUTY ETERNAL" NameC="永遠美麗" JockeyNameE="Z Purton" JockeyNameC="潘頓"/>
</race>
<race num="4">
<Tip Position="1" RunnerNumber="3" NameE="BRAVE DREAMS" NameC="勇敢夢想" JockeyNameE="Z Purton" JockeyNameC="潘頓"/>
<Tip Position="2" RunnerNumber="8" NameE="NOBLE ONE" NameC="魅力一丁" JockeyNameE="C Y Ho" JockeyNameC="何澤堯"/>
<Tip Position="3" RunnerNumber="4" NameE="HAPPY FOR ALL" NameC="四喜鳥" JockeyNameE="J McDonald" JockeyNameC="麥道朗"/>
<Tip Position="4" RunnerNumber="7" NameE="ROUND THE GLOBE" NameC="遨遊天下" JockeyNameE="K Teetan" JockeyNameC="田泰安"/>
</race>
<race num="5">
<Tip Position="1" RunnerNumber="8" NameE="SUPERB CAPITALIST" NameC="八駿巨昇" JockeyNameE="Y L Chung" JockeyNameC="鍾易禮"/>
<Tip Position="2" RunnerNumber="2" NameE="RUN RUN COOL" NameC="日日型" JockeyNameE="B Shinn" JockeyNameC="薛恩"/>
<Tip Position="3" RunnerNumber="4" NameE="LUCKY EIGHT" NameC="運高八斗" JockeyNameE="J Kah" JockeyNameC="賈傑美"/>
<Tip Position="4" RunnerNumber="3" NameE="SUPERB BOY" NameC="巴閉哥" JockeyNameE="H Bowman" JockeyNameC="布文"/>
</race>
<race num="6">
<Tip Position="1" RunnerNumber="7" NameE="THUNDERBOLTAURUS" NameC="霹靂神龍" JockeyNameE="H Bowman" JockeyNameC="布文"/>
<Tip Position="2" RunnerNumber="2" NameE="UNPRESUMING" NameC="色種笑" JockeyNameE="Z Purton" JockeyNameC="潘頓"/>
<Tip Position="3" RunnerNumber="4" NameE="KASI FARASI" NameC="一舖縱橫" JockeyNameE="K H Chan" JockeyNameC="陳嘉熙"/>
<Tip Position="4" RunnerNumber="6" NameE="BEAUTY MISSION" NameC="美麗攻略" JockeyNameE="A Badel" JockeyNameC="巴度"/>
</race>
<race num="7">
<Tip Position="1" RunnerNumber="2" NameE="ROMANTIC WARRIOR" NameC="浪漫勇士" JockeyNameE="K Teetan" JockeyNameC="田泰安"/>
<Tip Position="2" RunnerNumber="7" NameE="PANFIELD" NameC="勇戰神駒" JockeyNameE="H Bowman" JockeyNameC="布文"/>
<Tip Position="3" RunnerNumber="5" NameE="MONEY CATCHER" NameC="發財先鋒" JockeyNameE="S De Sousa" JockeyNameC="蘇兆輝"/>
<Tip Position="4" RunnerNumber="1" NameE="GOLDEN SIXTY" NameC="金鎗六十" JockeyNameE="C Y Ho" JockeyNameC="何澤堯"/>
</race>
<race num="8">
<Tip Position="1" RunnerNumber="6" NameE="ESCAPE ROUTE" NameC="波爾多" JockeyNameE="V Borges" JockeyNameC="波健士"/>
<Tip Position="2" RunnerNumber="3" NameE="WOODFIRE BRO" NameC="木火兄弟" JockeyNameE="K C Leung" JockeyNameC="梁家俊"/>
<Tip Position="3" RunnerNumber="8" NameE="S J TOURBILLON" NameC="三江飛輪" JockeyNameE="H Bowman" JockeyNameC="布文"/>
<Tip Position="4" RunnerNumber="7" NameE="HAPPY TOGETHER" NameC="越駿歡欣" JockeyNameE="A Badel" JockeyNameC="巴度"/>
</race>
<race num="9">
<Tip Position="1" RunnerNumber="2" NameE="VOYAGE BUBBLE" NameC="遨遊氣泡" JockeyNameE="J Kah" JockeyNameC="賈傑美"/>
<Tip Position="2" RunnerNumber="1" NameE="KEEFY" NameC="瑪瑙" JockeyNameE="K C Leung" JockeyNameC="梁家俊"/>
<Tip Position="3" RunnerNumber="10" NameE="ENCOUNTERED" NameC="安遇" JockeyNameE="S De Sousa" JockeyNameC="蘇兆輝"/>
<Tip Position="4" RunnerNumber="8" NameE="SUPER SUNNY SING" NameC="新力高升" JockeyNameE="C Y Ho" JockeyNameC="何澤堯"/>
</race>
<race num="10">
<Tip Position="1" RunnerNumber="1" NameE="NOT USUAL STAR" NameC="非凡之星" JockeyNameE="Y L Chung" JockeyNameC="鍾易禮"/>
<Tip Position="2" RunnerNumber="2" NameE="NEVER TOO SOON" NameC="快搏" JockeyNameE="J McDonald" JockeyNameC="麥道朗"/>
<Tip Position="3" RunnerNumber="7" NameE="ERIMO" NameC="烈風" JockeyNameE="K Teetan" JockeyNameC="田泰安"/>
<Tip Position="4" RunnerNumber="6" NameE="STUNNING IMPACT" NameC="紅衣震撼" JockeyNameE="J Kah" JockeyNameC="賈傑美"/>
</race>
<!--
<trackside text=""/>
-->
</tips>
