<?xml version="1.0" encoding="UTF-8"?>
<tips>
<meeting date="08-02-2023" venue="HV" title="心水提供"/>
<race num="1">
<Tip Position="1" RunnerNumber="12" NameE="FOXHUNTER WAY" NameC="獵狐者威" JockeyNameE="C Y Ho" JockeyNameC="何澤堯"/>
<Tip Position="2" RunnerNumber="9" NameE="AMAZING NEWS" NameC="捷報" JockeyNameE="M L Yeung" JockeyNameC="楊明綸"/>
<Tip Position="3" RunnerNumber="8" NameE="OUR CREED" NameC="創建群英" JockeyNameE="A Badel" JockeyNameC="巴度"/>
<Tip Position="4" RunnerNumber="7" NameE="MEDIC ELITE" NameC="無敵精英" JockeyNameE="Y L Chung" JockeyNameC="鍾易禮"/>
</race>
<race num="2">
<Tip Position="1" RunnerNumber="6" NameE="HAPPY ANGEL" NameC="但求快活" JockeyNameE="Z Purton" JockeyNameC="潘頓"/>
<Tip Position="2" RunnerNumber="9" NameE="FOREVER GLORIOUS" NameC="龍船快" JockeyNameE="C Y Ho" JockeyNameC="何澤堯"/>
<Tip Position="3" RunnerNumber="3" NameE="FLYING SILVER" NameC="躡景追飛" JockeyNameE="H Bowman" JockeyNameC="布文"/>
<Tip Position="4" RunnerNumber="12" NameE="REACH GOAL" NameC="一舖到位" JockeyNameE="A Badel" JockeyNameC="巴度"/>
</race>
<race num="3">
<Tip Position="1" RunnerNumber="8" NameE="PRIME MORTAR" NameC="砂漿金剛" JockeyNameE="K C Leung" JockeyNameC="梁家俊"/>
<Tip Position="2" RunnerNumber="9" NameE="LEATHER MASTER" NameC="皮具大師" JockeyNameE="C L Chau" JockeyNameC="周俊樂"/>
<Tip Position="3" RunnerNumber="11" NameE="GENERAL ACE" NameC="上浦精選" JockeyNameE="C Y Ho" JockeyNameC="何澤堯"/>
<Tip Position="4" RunnerNumber="7" NameE="ALLGREEKTOME" NameC="雅典武士" JockeyNameE="Z Purton" JockeyNameC="潘頓"/>
</race>
<race num="4">
<Tip Position="1" RunnerNumber="2" NameE="CALIFORNIA DEEPLY" NameC="加州得力" JockeyNameE="M Chadwick" JockeyNameC="蔡明紹"/>
<Tip Position="2" RunnerNumber="4" NameE="HEROIC MASTER" NameC="英雄豪邁" JockeyNameE="Z Purton" JockeyNameC="潘頓"/>
<Tip Position="3" RunnerNumber="1" NameE="METRO WARRIOR" NameC="精彩勇士" JockeyNameE="K H Chan" JockeyNameC="陳嘉熙"/>
<Tip Position="4" RunnerNumber="9" NameE="SUPER COMMANDER" NameC="令才" JockeyNameE="Y L Chung" JockeyNameC="鍾易禮"/>
</race>
<race num="5">
<Tip Position="1" RunnerNumber="12" NameE="HEARTY WISH" NameC="誠心所願" JockeyNameE="L Hewitson" JockeyNameC="希威森"/>
<Tip Position="2" RunnerNumber="10" NameE="ACE TALENT" NameC="天分高" JockeyNameE="C Y Ho" JockeyNameC="何澤堯"/>
<Tip Position="3" RunnerNumber="2" NameE="FORTE" NameC="風流人物" JockeyNameE="H Bowman" JockeyNameC="布文"/>
<Tip Position="4" RunnerNumber="7" NameE="E UNIVERSE" NameC="電子宇宙" JockeyNameE="Y L Chung" JockeyNameC="鍾易禮"/>
</race>
<race num="6">
<Tip Position="1" RunnerNumber="3" NameE="BEAUTY TYCOON" NameC="美麗笑聲" JockeyNameE="Z Purton" JockeyNameC="潘頓"/>
<Tip Position="2" RunnerNumber="4" NameE="EXCELLENT PEERS" NameC="越駿知己" JockeyNameE="M Chadwick" JockeyNameC="蔡明紹"/>
<Tip Position="3" RunnerNumber="9" NameE="XPONENTIAL" NameC="量化歡騰" JockeyNameE="S De Sousa" JockeyNameC="蘇兆輝"/>
<Tip Position="4" RunnerNumber="2" NameE="KING LAND" NameC="勁才" JockeyNameE="C L Chau" JockeyNameC="周俊樂"/>
</race>
<race num="7">
<Tip Position="1" RunnerNumber="2" NameE="FANTASTIC TREASURE" NameC="佳運財" JockeyNameE="L Currie" JockeyNameC="嘉里"/>
<Tip Position="2" RunnerNumber="7" NameE="BEAUTY LIVE" NameC="美麗在線" JockeyNameE="K C Leung" JockeyNameC="梁家俊"/>
<Tip Position="3" RunnerNumber="1" NameE="BERLIN TANGO" NameC="柏林探戈" JockeyNameE="H Bowman" JockeyNameC="布文"/>
<Tip Position="4" RunnerNumber="5" NameE="PACKING AWARD" NameC="包裝大獎" JockeyNameE="Z Purton" JockeyNameC="潘頓"/>
</race>
<race num="8">
<Tip Position="1" RunnerNumber="5" NameE="REWARDING TOGETHER" NameC="駿馬風采" JockeyNameE="S De Sousa" JockeyNameC="蘇兆輝"/>
<Tip Position="2" RunnerNumber="7" NameE="PING HAI GALAXY" NameC="平海歡星" JockeyNameE="K Teetan" JockeyNameC="田泰安"/>
<Tip Position="3" RunnerNumber="6" NameE="HANDSOME BO BO" NameC="艮志騰雲" JockeyNameE="M F Poon" JockeyNameC="潘明輝"/>
<Tip Position="4" RunnerNumber="9" NameE="FAMILY FOLKS" NameC="齊齊友福" JockeyNameE="A Hamelin" JockeyNameC="賀銘年"/>
</race>
<race num="9">
<Tip Position="1" RunnerNumber="4" NameE="RISING FROM ASHES" NameC="自力更生" JockeyNameE="K C Leung" JockeyNameC="梁家俊"/>
<Tip Position="2" RunnerNumber="3" NameE="ENCOUNTERED" NameC="安遇" JockeyNameE="S De Sousa" JockeyNameC="蘇兆輝"/>
<Tip Position="3" RunnerNumber="6" NameE="ALL BEAUTY" NameC="美麗滿滿" JockeyNameE="C Y Ho" JockeyNameC="何澤堯"/>
<Tip Position="4" RunnerNumber="2" NameE="VIVA CHALEUR" NameC="爆熱" JockeyNameE="H Bowman" JockeyNameC="布文"/>
</race>
<!--
<trackside text=""/>
-->
</tips>
