<?xml version="1.0" encoding="UTF-8"?>
<tips>
<meeting date="28-06-2025" venue="ST" title="心水提供"/>
<race num="1">
<Tip Position="1" RunnerNumber="2" NameE="TEAM HAPPY" NameC="添喜運" JockeyNameE="E C W Wong" JockeyNameC="黃智弘"/>
<Tip Position="2" RunnerNumber="13" NameE="JOYFUL FRIENDSHIP" NameC="友誼喜悅" JockeyNameE="A Atzeni" JockeyNameC="艾兆禮"/>
<Tip Position="3" RunnerNumber="6" NameE="NINJA DERBY" NameC="瀧澤飛駒" JockeyNameE="Y L Chung" JockeyNameC="鍾易禮"/>
<Tip Position="4" RunnerNumber="1" NameE="GALLANT CROWN" NameC="冠寶駒" JockeyNameE="B Avdulla" JockeyNameC="艾道拿"/>
</race>
<race num="2">
<Tip Position="1" RunnerNumber="2" NameE="BINGO BABE" NameC="東方福寶" JockeyNameE="Z Purton" JockeyNameC="潘頓"/>
<Tip Position="2" RunnerNumber="1" NameE="SIGHT DREAMER" NameC="巧眼光" JockeyNameE="B Avdulla" JockeyNameC="艾道拿"/>
<Tip Position="3" RunnerNumber="3" NameE="DRACO" NameC="快樂老撾" JockeyNameE="J Orman" JockeyNameC="奧爾民"/>
<Tip Position="4" RunnerNumber="14" NameE="SPEEDY SMARTIE" NameC="伶俐驫駒" JockeyNameE="A Atzeni" JockeyNameC="艾兆禮"/>
</race>
<race num="3">
<Tip Position="1" RunnerNumber="7" NameE="AGENDA" NameC="清雲龍駒" JockeyNameE="K Teetan" JockeyNameC="田泰安"/>
<Tip Position="2" RunnerNumber="6" NameE="GENTLEMEN LEGACY" NameC="君子傳承" JockeyNameE="Z Purton" JockeyNameC="潘頓"/>
<Tip Position="3" RunnerNumber="3" NameE="FAMILY JEWEL" NameC="共享富裕" JockeyNameE="E C W Wong" JockeyNameC="黃智弘"/>
<Tip Position="4" RunnerNumber="9" NameE="PACKING HURRICANE" NameC="包裝旋風" JockeyNameE="Y L Chung" JockeyNameC="鍾易禮"/>
</race>
<race num="4">
<Tip Position="1" RunnerNumber="4" NameE="GOLDENTRONICMIGHTY" NameC="金創福威" JockeyNameE="B Avdulla" JockeyNameC="艾道拿"/>
<Tip Position="2" RunnerNumber="1" NameE="ABSOLUTE HONOUR" NameC="超開心" JockeyNameE="Y L Chung" JockeyNameC="鍾易禮"/>
<Tip Position="3" RunnerNumber="7" NameE="BETTER AND BETTER" NameC="天天更好" JockeyNameE="M L Yeung" JockeyNameC="楊明綸"/>
<Tip Position="4" RunnerNumber="11" NameE="SUNNY SING SPIRIT" NameC="新力超升" JockeyNameE="K Teetan" JockeyNameC="田泰安"/>
</race>
<race num="5">
<Tip Position="1" RunnerNumber="7" NameE="MANAGEMENT FOLKS" NameC="管之友" JockeyNameE="M F Poon" JockeyNameC="潘明輝"/>
<Tip Position="2" RunnerNumber="4" NameE="S J TOURBILLON" NameC="三江飛輪" JockeyNameE="E C W Wong" JockeyNameC="黃智弘"/>
<Tip Position="3" RunnerNumber="13" NameE="STORM RUNNER" NameC="步風雷" JockeyNameE="M Chadwick" JockeyNameC="蔡明紹"/>
<Tip Position="4" RunnerNumber="1" NameE="FAST SPEED" NameC="勁步速" JockeyNameE="H T Mo" JockeyNameC="巫顯東"/>
</race>
<race num="6">
<Tip Position="1" RunnerNumber="12" NameE="SOLAR RIVER" NameC="洛河" JockeyNameE="A Hamelin" JockeyNameC="賀銘年"/>
<Tip Position="2" RunnerNumber="6" NameE="ROMANTIC PARTY" NameC="浪漫喜宴" JockeyNameE="H Bentley" JockeyNameC="班德禮"/>
<Tip Position="3" RunnerNumber="2" NameE="SOLID IMPACT" NameC="實力派" JockeyNameE="Z Purton" JockeyNameC="潘頓"/>
<Tip Position="4" RunnerNumber="1" NameE="LUCKY MY WAY" NameC="幸運多彩" JockeyNameE="K C Leung" JockeyNameC="梁家俊"/>
</race>
<race num="7">
<Tip Position="1" RunnerNumber="1" NameE="MEGA FORCE" NameC="十力" JockeyNameE="J Orman" JockeyNameC="奧爾民"/>
<Tip Position="2" RunnerNumber="7" NameE="STORMI" NameC="翠兒威威" JockeyNameE="H Bentley" JockeyNameC="班德禮"/>
<Tip Position="3" RunnerNumber="8" NameE="ICONICAL" NameC="飈誌" JockeyNameE="A Atzeni" JockeyNameC="艾兆禮"/>
<Tip Position="4" RunnerNumber="6" NameE="PRECISION GOAL" NameC="天時明駒" JockeyNameE="L Ferraris" JockeyNameC="霍宏聲"/>
</race>
<race num="8">
<Tip Position="1" RunnerNumber="2" NameE="WUNDERBAR" NameC="氣勢" JockeyNameE="B Avdulla" JockeyNameC="艾道拿"/>
<Tip Position="2" RunnerNumber="6" NameE="HORSEPOWER" NameC="馬力" JockeyNameE="Z Purton" JockeyNameC="潘頓"/>
<Tip Position="3" RunnerNumber="4" NameE="AURORA LADY" NameC="晨曦儷人" JockeyNameE="M F Poon" JockeyNameC="潘明輝"/>
<Tip Position="4" RunnerNumber="5" NameE="FULL CREDIT" NameC="同祥和順" JockeyNameE="M Chadwick" JockeyNameC="蔡明紹"/>
</race>
<race num="9">
<Tip Position="1" RunnerNumber="6" NameE="SECOND TO NONE" NameC="獨步天下" JockeyNameE="K De Melo" JockeyNameC="董明朗"/>
<Tip Position="2" RunnerNumber="3" NameE="KA YING GLORY" NameC="嘉應駿昇" JockeyNameE="Z Purton" JockeyNameC="潘頓"/>
<Tip Position="3" RunnerNumber="10" NameE="GOLDEN LUCK" NameC="金運來" JockeyNameE="E C W Wong" JockeyNameC="黃智弘"/>
<Tip Position="4" RunnerNumber="5" NameE="OLDTOWN" NameC="鋁神" JockeyNameE="J Orman" JockeyNameC="奧爾民"/>
</race>
<race num="10">
<Tip Position="1" RunnerNumber="11" NameE="LUCKY TOUCH" NameC="勝意" JockeyNameE="A Atzeni" JockeyNameC="艾兆禮"/>
<Tip Position="2" RunnerNumber="5" NameE="MOJAVE DESERT" NameC="智跑得" JockeyNameE="K C Leung" JockeyNameC="梁家俊"/>
<Tip Position="3" RunnerNumber="6" NameE="CHILL KAKA" NameC="超加加" JockeyNameE="Z Purton" JockeyNameC="潘頓"/>
<Tip Position="4" RunnerNumber="12" NameE="ORIENTAL SMOKE" NameC="東方飛影" JockeyNameE="B Thompson" JockeyNameC="湯普新"/>
</race>
<race num="11">
<Tip Position="1" RunnerNumber="3" NameE="KA YING ATTACK" NameC="嘉應奇兵" JockeyNameE="M F Poon" JockeyNameC="潘明輝"/>
<Tip Position="2" RunnerNumber="8" NameE="MR BOLT" NameC="飛馬先生" JockeyNameE="A Atzeni" JockeyNameC="艾兆禮"/>
<Tip Position="3" RunnerNumber="2" NameE="SUGAR SUGAR" NameC="鈁糖武士" JockeyNameE="E C W Wong" JockeyNameC="黃智弘"/>
<Tip Position="4" RunnerNumber="10" NameE="FIND MY LOVE" NameC="紅愛舍" JockeyNameE="K De Melo" JockeyNameC="董明朗"/>
</race>
<!--
<trackside text=""/>
-->
</tips>
