<?xml version="1.0" encoding="UTF-8"?>
<tips>
<meeting date="20-10-2021" venue="HV" title="心水提供"/>
<race num="1">
<Tip Position="1" RunnerNumber="8" NameE="ALLOY KING" NameC="合金皇" JockeyNameE="A Hamelin" JockeyNameC="賀銘年"/>
<Tip Position="2" RunnerNumber="9" NameE="GOLDEN MISSION" NameC="金剛石" JockeyNameE="H Bentley" JockeyNameC="班德禮"/>
<Tip Position="3" RunnerNumber="10" NameE="SUNNY SMILE" NameC="威力喜" JockeyNameE="C L Chau" JockeyNameC="周俊樂"/>
<Tip Position="4" RunnerNumber="6" NameE="DAY DAY RICH" NameC="天天智庫" JockeyNameE="B Shinn" JockeyNameC="薛恩"/>
</race>
<race num="2">
<Tip Position="1" RunnerNumber="2" NameE="VIVA POPCORN" NameC="爆谷" JockeyNameE="Z Purton" JockeyNameC="潘頓"/>
<Tip Position="2" RunnerNumber="8" NameE="SUPER KIN" NameC="堅有料" JockeyNameE="J Moreira" JockeyNameC="莫雷拉"/>
<Tip Position="3" RunnerNumber="12" NameE="MANY GAINS" NameC="喜又盈" JockeyNameE="H W Lai" JockeyNameC="黎海榮"/>
<Tip Position="4" RunnerNumber="6" NameE="HAPPY JAI JAI" NameC="又享耆成" JockeyNameE="M L Yeung" JockeyNameC="楊明綸"/>
</race>
<race num="3">
<Tip Position="1" RunnerNumber="12" NameE="HAPPY GATHERING" NameC="大家開心" JockeyNameE="M Chadwick" JockeyNameC="蔡明紹"/>
<Tip Position="2" RunnerNumber="6" NameE="HAPPILY FRIENDS" NameC="歡樂好友" JockeyNameE="C Y Ho" JockeyNameC="何澤堯"/>
<Tip Position="3" RunnerNumber="2" NameE="AMAZING NEWS" NameC="捷報" JockeyNameE="J Moreira" JockeyNameC="莫雷拉"/>
<Tip Position="4" RunnerNumber="1" NameE="NEW FUTURE" NameC="觀世界" JockeyNameE="C L Chau" JockeyNameC="周俊樂"/>
</race>
<race num="4">
<Tip Position="1" RunnerNumber="10" NameE="DESTIN" NameC="天意" JockeyNameE="M Chadwick" JockeyNameC="蔡明紹"/>
<Tip Position="2" RunnerNumber="5" NameE="PRANCE DRAGON" NameC="騰龍駒" JockeyNameE="C Y Ho" JockeyNameC="何澤堯"/>
<Tip Position="3" RunnerNumber="12" NameE="SPLIT OF A SECOND" NameC="銀亮之星" JockeyNameE="V Borges" JockeyNameC="波健士"/>
<Tip Position="4" RunnerNumber="7" NameE="A SMILE LIKE YOURS" NameC="銘記知心" JockeyNameE="K Teetan" JockeyNameC="田泰安"/>
</race>
<race num="5">
<Tip Position="1" RunnerNumber="2" NameE="RED MAJESTY" NameC="赤馬雄風" JockeyNameE="Z Purton" JockeyNameC="潘頓"/>
<Tip Position="2" RunnerNumber="10" NameE="STAY CHILL" NameC="安逸寧靜" JockeyNameE="M L Yeung" JockeyNameC="楊明綸"/>
<Tip Position="3" RunnerNumber="9" NameE="ALL YOU KNOW" NameC="快利寶" JockeyNameE="M F Poon" JockeyNameC="潘明輝"/>
<Tip Position="4" RunnerNumber="1" NameE="LOYAL BABY" NameC="忠誠駒" JockeyNameE="C Schofield" JockeyNameC="史卓豐"/>
</race>
<race num="6">
<Tip Position="1" RunnerNumber="6" NameE="BRILLIANT FORTUNE" NameC="智醒財星" JockeyNameE="J Moreira" JockeyNameC="莫雷拉"/>
<Tip Position="2" RunnerNumber="2" NameE="HARMONY N BLESSED" NameC="人和家興" JockeyNameE="Z Purton" JockeyNameC="潘頓"/>
<Tip Position="3" RunnerNumber="4" NameE="HARMONY FIRE" NameC="天火同人" JockeyNameE="C L Chau" JockeyNameC="周俊樂"/>
<Tip Position="4" RunnerNumber="8" NameE="CANTSTOPTHEFEELING" NameC="無限商機" JockeyNameE="V Borges" JockeyNameC="波健士"/>
</race>
<race num="7">
<Tip Position="1" RunnerNumber="2" NameE="NOBLE DESIRE" NameC="魅力星光" JockeyNameE="C L Chau" JockeyNameC="周俊樂"/>
<Tip Position="2" RunnerNumber="10" NameE="PRINCE OF BON BON" NameC="信威王子" JockeyNameE="C Y Ho" JockeyNameC="何澤堯"/>
<Tip Position="3" RunnerNumber="11" NameE="TOUCH FAITH" NameC="當家信心" JockeyNameE="J Moreira" JockeyNameC="莫雷拉"/>
<Tip Position="4" RunnerNumber="5" NameE="WHISKEY NEAT" NameC="大醇威" JockeyNameE="B Shinn" JockeyNameC="薛恩"/>
</race>
<race num="8">
<Tip Position="1" RunnerNumber="11" NameE="WOOD ON FIRE" NameC="木火同明" JockeyNameE="K Teetan" JockeyNameC="田泰安"/>
<Tip Position="2" RunnerNumber="8" NameE="EVER FORCE" NameC="零距離" JockeyNameE="J Moreira" JockeyNameC="莫雷拉"/>
<Tip Position="3" RunnerNumber="9" NameE="HARRIER JET" NameC="騰龍超影" JockeyNameE="V Borges" JockeyNameC="波健士"/>
<Tip Position="4" RunnerNumber="4" NameE="FAMILY FOLKS" NameC="齊齊友福" JockeyNameE="H Bentley" JockeyNameC="班德禮"/>
</race>
<race num="9">
<Tip Position="1" RunnerNumber="6" NameE="FA FA" NameC="俏芳華" JockeyNameE="C Y Ho" JockeyNameC="何澤堯"/>
<Tip Position="2" RunnerNumber="9" NameE="TOTAL POWER" NameC="勁駒" JockeyNameE="H T Mo" JockeyNameC="巫顯東"/>
<Tip Position="3" RunnerNumber="5" NameE="PARTERRE" NameC="拍馬難追" JockeyNameE="K Teetan" JockeyNameC="田泰安"/>
<Tip Position="4" RunnerNumber="1" NameE="FARSHAD" NameC="童話" JockeyNameE="M Chadwick" JockeyNameC="蔡明紹"/>
</race>
<!--
<trackside text=""/>
-->
</tips>
