<?xml version="1.0" encoding="UTF-8"?>
<tips>
<meeting date="27-04-2025" venue="ST" title="心水提供"/>
<race num="1">
<Tip Position="1" RunnerNumber="6" NameE="SMILING COLLECTOR" NameC="聚風雲" JockeyNameE="H Bentley" JockeyNameC="班德禮"/>
<Tip Position="2" RunnerNumber="5" NameE="VOLCANIC SPARK" NameC="風火恆雲" JockeyNameE="J McDonald" JockeyNameC="麥道朗"/>
<Tip Position="3" RunnerNumber="1" NameE="MATSU VICTOR" NameC="江南勇士" JockeyNameE="J Moreira" JockeyNameC="莫雷拉"/>
<Tip Position="4" RunnerNumber="9" NameE="YOUTH POWER" NameC="青春力量" JockeyNameE="K Teetan" JockeyNameC="田泰安"/>
</race>
<race num="2">
<Tip Position="1" RunnerNumber="6" NameE="BEAUTY MISSILE" NameC="特別美麗" JockeyNameE="A Hamelin" JockeyNameC="賀銘年"/>
<Tip Position="2" RunnerNumber="1" NameE="AEROINVINCIBLE" NameC="友瑩仁" JockeyNameE="J Orman" JockeyNameC="奧爾民"/>
<Tip Position="3" RunnerNumber="2" NameE="PARTERRE" NameC="拍馬難追" JockeyNameE="J Moreira" JockeyNameC="莫雷拉"/>
<Tip Position="4" RunnerNumber="4" NameE="PATCH OF TIME" NameC="手錶之星" JockeyNameE="L Hewitson" JockeyNameC="希威森"/>
</race>
<race num="3">
<Tip Position="1" RunnerNumber="5" NameE="MONARCH COUNTY" NameC="仁仁有餘" JockeyNameE="J Moreira" JockeyNameC="莫雷拉"/>
<Tip Position="2" RunnerNumber="9" NameE="PATCH OF STARS" NameC="錶之星河" JockeyNameE="Z Purton" JockeyNameC="潘頓"/>
<Tip Position="3" RunnerNumber="4" NameE="FORERUNNER" NameC="博愛先鋒" JockeyNameE="C Williams" JockeyNameC="韋紀力"/>
<Tip Position="4" RunnerNumber="11" NameE="WIN SPEED" NameC="超風速" JockeyNameE="M Chadwick" JockeyNameC="蔡明紹"/>
</race>
<race num="4">
<Tip Position="1" RunnerNumber="4" NameE="YOUNG CHAMPION" NameC="競駿輝煌" JockeyNameE="B Avdulla" JockeyNameC="艾道拿"/>
<Tip Position="2" RunnerNumber="2" NameE="DIVANO" NameC="開心寶寶" JockeyNameE="Z Purton" JockeyNameC="潘頓"/>
<Tip Position="3" RunnerNumber="6" NameE="INVINCIBLE SHIELD" NameC="笑傲江湖" JockeyNameE="C Williams" JockeyNameC="韋紀力"/>
<Tip Position="4" RunnerNumber="10" NameE="MARKWIN" NameC="但求開心" JockeyNameE="H Bentley" JockeyNameC="班德禮"/>
</race>
<race num="5">
<Tip Position="1" RunnerNumber="2" NameE="SATONO REVE" NameC="里見夢境" JockeyNameE="J Moreira" JockeyNameC="莫雷拉"/>
<Tip Position="2" RunnerNumber="10" NameE="BEAUTY WAVES" NameC="美麗第一" JockeyNameE="A Atzeni" JockeyNameC="艾兆禮"/>
<Tip Position="3" RunnerNumber="12" NameE="COPARTNER PRANCE" NameC="合夥奔馳" JockeyNameE="J Orman" JockeyNameC="奧爾民"/>
<Tip Position="4" RunnerNumber="6" NameE="HELIOS EXPRESS" NameC="驕陽明駒" JockeyNameE="H Bowman" JockeyNameC="布文"/>
</race>
<race num="6">
<Tip Position="1" RunnerNumber="3" NameE="GENEVA" NameC="增強" JockeyNameE="B Avdulla" JockeyNameC="艾道拿"/>
<Tip Position="2" RunnerNumber="4" NameE="MASTEROFMYUNIVERSE" NameC="真心傳奇" JockeyNameE="Z Purton" JockeyNameC="潘頓"/>
<Tip Position="3" RunnerNumber="5" NameE="SUPER LEGENDS" NameC="非凡達" JockeyNameE="J McDonald" JockeyNameC="麥道朗"/>
<Tip Position="4" RunnerNumber="1" NameE="CALL ME GLORIOUS" NameC="龍之輝" JockeyNameE="J Orman" JockeyNameC="奧爾民"/>
</race>
<race num="7">
<Tip Position="1" RunnerNumber="4" NameE="BEAUTY ETERNAL" NameC="永遠美麗" JockeyNameE="A Atzeni" JockeyNameC="艾兆禮"/>
<Tip Position="2" RunnerNumber="6" NameE="GALAXY PATCH" NameC="錶之銀河" JockeyNameE="Z Purton" JockeyNameC="潘頓"/>
<Tip Position="3" RunnerNumber="12" NameE="MY WISH" NameC="祝願" JockeyNameE="L Ferraris" JockeyNameC="霍宏聲"/>
<Tip Position="4" RunnerNumber="1" NameE="MR BRIGHTSIDE" NameC="樂觀派" JockeyNameE="C Williams" JockeyNameC="韋紀力"/>
</race>
<race num="8">
<Tip Position="1" RunnerNumber="9" NameE="CAP FERRAT" NameC="百賀飛駒" JockeyNameE="C Williams" JockeyNameC="韋紀力"/>
<Tip Position="2" RunnerNumber="7" NameE="ENSUED" NameC="安騁" JockeyNameE="B Avdulla" JockeyNameC="艾道拿"/>
<Tip Position="3" RunnerNumber="2" NameE="PROGNOSIS" NameC="先見" JockeyNameE="J McDonald" JockeyNameC="麥道朗"/>
<Tip Position="4" RunnerNumber="5" NameE="EL VENCEDOR" NameC="贏家" JockeyNameE="Z Purton" JockeyNameC="潘頓"/>
</race>
<race num="9">
<Tip Position="1" RunnerNumber="6" NameE="STAR MAC" NameC="久久為尊" JockeyNameE="B Avdulla" JockeyNameC="艾道拿"/>
<Tip Position="2" RunnerNumber="4" NameE="SUPERB KID" NameC="巴閉仔" JockeyNameE="A Atzeni" JockeyNameC="艾兆禮"/>
<Tip Position="3" RunnerNumber="3" NameE="HUGE WAVE" NameC="大浪圖田" JockeyNameE="H Bowman" JockeyNameC="布文"/>
<Tip Position="4" RunnerNumber="1" NameE="TOURBILLON PRINCE" NameC="飛輪步" JockeyNameE="Z Purton" JockeyNameC="潘頓"/>
</race>
<race num="10">
<Tip Position="1" RunnerNumber="4" NameE="ENDEARED" NameC="安泰" JockeyNameE="C Williams" JockeyNameC="韋紀力"/>
<Tip Position="2" RunnerNumber="11" NameE="SUPREME AGILITY" NameC="奮鬥心" JockeyNameE="M F Poon" JockeyNameC="潘明輝"/>
<Tip Position="3" RunnerNumber="2" NameE="CHARMING BABE" NameC="輕功猛男" JockeyNameE="A Hamelin" JockeyNameC="賀銘年"/>
<Tip Position="4" RunnerNumber="3" NameE="SILVERY BREEZE" NameC="銀亮奔騰" JockeyNameE="K Teetan" JockeyNameC="田泰安"/>
</race>
<!--
<trackside text=""/>
-->
</tips>
